bilby_tgr/__init__.py
bilby_tgr/_version.py
bilby_tgr/fti/README.rst
bilby_tgr/fti/__init__.py
bilby_tgr/fti/conversion.py
bilby_tgr/fti/prior.py
bilby_tgr/fti/source.py
bilby_tgr/fti/prior_files/aligned_spins_bbh.prior
bilby_tgr/fti/prior_files/aligned_spins_bns_tides_on.prior
bilby_tgr/fti/prior_files/precessing_spins_bbh.prior
bilby_tgr/fti/prior_files/precessing_spins_bns_tides_on.prior
bilby_tgr/mdr/__init__.py
bilby_tgr/mdr/conversion.py
bilby_tgr/mdr/postprocessing.py
bilby_tgr/mdr/prior.py
bilby_tgr/mdr/source.py
bilby_tgr/mdr/prior_files/aligned_spins_bbh.prior
bilby_tgr/mdr/prior_files/aligned_spins_bbh_tides_on.prior
bilby_tgr/mdr/prior_files/aligned_spins_bns.prior
bilby_tgr/mdr/prior_files/aligned_spins_bns_tides_on.prior
bilby_tgr/mdr/prior_files/precessing_spins_bbh.prior
bilby_tgr/mdr/prior_files/precessing_spins_bbh_tides_on.prior
bilby_tgr/mdr/prior_files/precessing_spins_bns.prior
bilby_tgr/mdr/prior_files/precessing_spins_bns_tides_on.prior
bilby_tgr/pseob/README.rst
bilby_tgr/pseob/__init__.py
bilby_tgr/pseob/prior.py
bilby_tgr/pseob/source.py
bilby_tgr/pseob/prior_files/aligned_spins_bbh.prior
bilby_tgr/pseob/prior_files/aligned_spins_bbh_v4.prior
bilby_tgr/pseob/prior_files/precessing_spins_bbh.prior
bilby_tgr/siqm/README.rst
bilby_tgr/siqm/__init__.py
bilby_tgr/siqm/conversion.py
bilby_tgr/siqm/prior.py
bilby_tgr/siqm/source.py
bilby_tgr/siqm/prior_files/aligned_spins_bbh.prior
bilby_tgr/siqm/prior_files/precessing_spins_bbh.prior
bilby_tgr/ssb/__init__.py
bilby_tgr/ssb/conversion.py
bilby_tgr/ssb/source.py
bilby_tgr/tiger/__init__.py
bilby_tgr/tiger/source.py
bilby_tgr-0.2.dist-info/LICENSE.md
bilby_tgr-0.2.dist-info/METADATA
bilby_tgr-0.2.dist-info/WHEEL
bilby_tgr-0.2.dist-info/top_level.txt
bilby_tgr-0.2.dist-info/RECORD
