Metadata-Version: 2.2
Name: bilby_tgr
Version: 0.2
Summary: Testing GR analysis pipelines to use with Bilby
Author: Colm Talbot, Soumen Roy, Geraint Pratten, Tsun-Ho Pang, Tomasz Baka, Elise Sänger, Ajit Mehta, Jan Steinhoff, Elisa Maggio, Abhirup Ghosh, Stanislav Babak, Gregorio Carullo, Danny Laghi, Haris K, Balazs Cirok, Krishnendu N V, Naresh Adhikari, Anuradha Gupta, Ish Gupta, Aditya Vijaykumar, Raffi Enficiaud, Lorenzo Pompili
Author-email: Gregory Ashton <gregory.ashton@ligo.org>, Michalis Agathos <michalis.agathos@ligo.org>
Maintainer: Aditya Vijaykumar
Maintainer-email: Michalis Agathos <michalis.agathos@ligo.org>
License: MIT
Project-URL: repository, https://git.ligo.org/lscsoft/bilby_tgr
Classifier: Programming Language :: Python :: 3
Classifier: License :: OSI Approved :: MIT License
Classifier: Operating System :: OS Independent
Classifier: Intended Audience :: Science/Research
Classifier: Topic :: Scientific/Engineering :: Physics
Classifier: Topic :: Scientific/Engineering :: Astronomy
Requires-Python: >=3.8
License-File: LICENSE.md
Requires-Dist: bilby
Requires-Dist: lalsuite>=7.20
Requires-Dist: numpy>=1.17
Requires-Dist: scipy==1.14.0
Provides-Extra: automation
Requires-Dist: cbcflow>=0.2.2; extra == "automation"
Requires-Dist: asimov>=0.5.0b11; extra == "automation"
